setup.py
codesnips/__init__.py
codesnips/fields.py
codesnips/mixins.py
codesnips/middleware/__init__.py
codesnips/middleware/crossdomainxhr.py
codesnips/middleware/requirelogin.py
django_codesnips.egg-info/PKG-INFO
django_codesnips.egg-info/SOURCES.txt
django_codesnips.egg-info/dependency_links.txt
django_codesnips.egg-info/requires.txt
django_codesnips.egg-info/top_level.txt