Metadata-Version: 1.1
Name: django-codesnips
Version: 0.1.0
Summary: Django code snippets
Home-page: https://github.com/PacketPerception/django-codesnips
Author: UNKNOWN
Author-email: opensource(at)packetperception.org
License: MIT
Keywords: Django
Platform: UNKNOWN
Classifier: Programming Language :: Python
Classifier: Intended Audience :: Developers
Classifier: License :: OSI Approved :: MIT License
Classifier: Operating System :: OS Independent
Classifier: Framework :: Django
